{
	"instance" : {
		"lineStyleSelector" : "ManuelLeuenberger 10/27/2017 14:01",
		"asWidget" : "ManuelLeuenberger 10/27/2017 14:04",
		"email" : "ManuelLeuenberger 10/27/2017 14:01",
		"country" : "ManuelLeuenberger 10/27/2017 14:01",
		"email:" : "ManuelLeuenberger 10/27/2017 14:01",
		"country:" : "ManuelLeuenberger 10/27/2017 14:01",
		"institution" : "ManuelLeuenberger 10/27/2017 14:01",
		"institution:" : "ManuelLeuenberger 10/27/2017 14:01"
	},
	"class" : {
		"sourceClass" : "ManuelLeuenberger 10/27/2017 14:01",
		"label" : "ManuelLeuenberger 10/27/2017 14:01",
		"targetClass" : "ManuelLeuenberger 10/27/2017 14:01",
		"graph:source:target:key:email:institution:country:" : "ManuelLeuenberger 10/27/2017 14:01"
	}
}